cargo/__init__.py
cargo/cargo.py
shell/__init__.py
shell/shell.py
cargolang-1.1.1.dist-info/METADATA
cargolang-1.1.1.dist-info/WHEEL
cargolang-1.1.1.dist-info/entry_points.txt
cargolang-1.1.1.dist-info/top_level.txt
cargolang-1.1.1.dist-info/RECORD
