Metadata-Version: 2.1
Name: cargolang
Version: 1.1.1
Summary: UNKNOWN
Author: Cargo
License: UNKNOWN
Platform: UNKNOWN
Requires-Dist: click
Requires-Dist: osascript
